meteors/__init__.py
meteors/exceptions.py
meteors/hsi.py
meteors/utils.py
meteors/attr/__init__.py
meteors/attr/attributes.py
meteors/attr/explainer.py
meteors/attr/input_x_gradients.py
meteors/attr/integrated_gradients.py
meteors/attr/lime.py
meteors/attr/lime_base.py
meteors/attr/noise_tunnel.py
meteors/attr/occlusion.py
meteors/attr/saliency.py
meteors/models/__init__.py
meteors/models/abstract.py
meteors/models/linear.py
meteors/visualize/__init__.py
meteors/visualize/attr_visualize.py
meteors/visualize/hsi_visualize.py
meteors-0.2.0.dist-info/METADATA
meteors-0.2.0.dist-info/WHEEL
meteors-0.2.0.dist-info/licenses/LICENSE
meteors-0.2.0.dist-info/RECORD
