Metadata-Version: 2.3
Name: meteors
Version: 0.2.0
Summary: Explanations of models for Hyperspectral data
Project-URL: Homepage, https://github.com/xai4space/meteors/
Author-email: Tymoteusz Kwiecinski <tymoteuszkwiecinski@gmail.com>
License: BSD-3-Clause
Classifier: Development Status :: 2 - Pre-Alpha
Classifier: Programming Language :: Python :: 3
Classifier: Programming Language :: Python :: 3.9
Classifier: Programming Language :: Python :: 3.10
Classifier: Programming Language :: Python :: 3.11
Classifier: Programming Language :: Python :: 3.12
Requires-Python: >=3.9
Requires-Dist: captum>=0.7.0
Requires-Dist: eval-type-backport
Requires-Dist: importlib-resources; python_version < '3.10'
Requires-Dist: loguru
Requires-Dist: matplotlib
Requires-Dist: numpy<2.0.0
Requires-Dist: pandas
Requires-Dist: pydantic
Requires-Dist: scikit-image
Requires-Dist: scikit-learn
Requires-Dist: seaborn
Requires-Dist: setuptools>=60.0.0
Requires-Dist: spyndex>=0.6.0
Requires-Dist: torch>=1.10
